aws_export_credentials/__init__.py
aws_export_credentials/__main__.py
aws_export_credentials/aws_export_credentials.py
aws_export_credentials/config_file_writer.py
aws_export_credentials-0.18.0.dist-info/LICENSE
aws_export_credentials-0.18.0.dist-info/METADATA
aws_export_credentials-0.18.0.dist-info/WHEEL
aws_export_credentials-0.18.0.dist-info/entry_points.txt
aws_export_credentials-0.18.0.dist-info/RECORD
