Metadata-Version: 2.1
Name: aws-export-credentials
Version: 0.18.0
Summary: Get AWS credentials from a profile to inject into other programs
Home-page: https://github.com/benkehoe/aws-export-credentials
License: Apache-2.0
Author: Ben Kehoe
Author-email: ben@kehoe.io
Requires-Python: >=3.7,<4.0
Classifier: Development Status :: 4 - Beta
Classifier: Intended Audience :: Developers
Classifier: Intended Audience :: System Administrators
Classifier: License :: OSI Approved :: Apache Software License
Classifier: Operating System :: OS Independent
Classifier: Programming Language :: Python :: 3
Classifier: Programming Language :: Python :: 3.7
Classifier: Programming Language :: Python :: 3.8
Classifier: Programming Language :: Python :: 3.9
Classifier: Programming Language :: Python :: 3.10
Classifier: Programming Language :: Python :: 3.11
Classifier: Topic :: Utilities
Requires-Dist: boto3 (>=1.14)
Project-URL: Repository, https://github.com/benkehoe/aws-export-credentials
